{
  "_generated": "Generated by SweetTooth, do not edit",
  "description": "Move and resize Picture-in-Picture windows according to your preferences, optionally keeping them always on top. A GNOME Shell extension designed for web browser PiP windows on Wayland. Works well with a multiple monitors setup.",
  "donations": {
    "kofi": "filiprund"
  },
  "gettext-domain": "in-picture@filiprund.cz",
  "name": "In Picture",
  "settings-schema": "org.gnome.shell.extensions.in-picture",
  "shell-version": [
    "48",
    "49",
    "50"
  ],
  "url": "https://codeberg.org/filiprund/in-picture",
  "uuid": "in-picture@filiprund.cz",
  "version": 8
}